LICENSE
MANIFEST.in
README.md
setup.py
django_mobile_auth.egg-info/PKG-INFO
django_mobile_auth.egg-info/SOURCES.txt
django_mobile_auth.egg-info/dependency_links.txt
django_mobile_auth.egg-info/requires.txt
django_mobile_auth.egg-info/top_level.txt
mobile_auth/__init__.py
mobile_auth/admin.py
mobile_auth/apps.py
mobile_auth/backends.py
mobile_auth/fields.py
mobile_auth/models.py
mobile_auth/tests.py
mobile_auth/validators.py
mobile_auth/management/__init__.py
mobile_auth/management/commands/__init__.py
mobile_auth/management/commands/createsuperuser.py
mobile_auth/migrations/0001_initial.py
mobile_auth/migrations/__init__.py