Metadata-Version: 1.1
Name: django-mobile-auth
Version: 0.2.5
Summary: A Django app that allows users to authenticate using email, phone number or username.
Home-page: https://github.com/ricardosasilva/django_mobile_auth
Author: Ricardo S. A. Silva
Author-email: ricardo@salamandra.cc
License: MIT
Keywords: django auth email phone
Platform: UNKNOWN
Classifier: Development Status :: 3 - Alpha
Classifier: Framework :: Django
Classifier: Intended Audience :: Developers
Classifier: License :: OSI Approved :: MIT License
Classifier: Operating System :: OS Independent
Classifier: Programming Language :: Python
Classifier: Programming Language :: Python :: 3
